aliyunsdkdts/__init__.py
aliyunsdkdts/endpoint.py
aliyunsdkdts/request/__init__.py
aliyunsdkdts/request/v20200101/ConfigureDtsJobRequest.py
aliyunsdkdts/request/v20200101/ConfigureMigrationJobAlertRequest.py
aliyunsdkdts/request/v20200101/ConfigureMigrationJobRequest.py
aliyunsdkdts/request/v20200101/ConfigureSubscriptionInstanceAlertRequest.py
aliyunsdkdts/request/v20200101/ConfigureSubscriptionInstanceRequest.py
aliyunsdkdts/request/v20200101/ConfigureSubscriptionRequest.py
aliyunsdkdts/request/v20200101/ConfigureSynchronizationJobAlertRequest.py
aliyunsdkdts/request/v20200101/ConfigureSynchronizationJobReplicatorCompareRequest.py
aliyunsdkdts/request/v20200101/ConfigureSynchronizationJobRequest.py
aliyunsdkdts/request/v20200101/CountJobByConditionRequest.py
aliyunsdkdts/request/v20200101/CreateConsumerChannelRequest.py
aliyunsdkdts/request/v20200101/CreateConsumerGroupRequest.py
aliyunsdkdts/request/v20200101/CreateDedicatedClusterMonitorRuleRequest.py
aliyunsdkdts/request/v20200101/CreateDtsInstanceRequest.py
aliyunsdkdts/request/v20200101/CreateJobMonitorRuleRequest.py
aliyunsdkdts/request/v20200101/CreateMigrationJobRequest.py
aliyunsdkdts/request/v20200101/CreateSubscriptionInstanceRequest.py
aliyunsdkdts/request/v20200101/CreateSynchronizationJobRequest.py
aliyunsdkdts/request/v20200101/DeleteConsumerChannelRequest.py
aliyunsdkdts/request/v20200101/DeleteConsumerGroupRequest.py
aliyunsdkdts/request/v20200101/DeleteDtsJobRequest.py
aliyunsdkdts/request/v20200101/DeleteDtsJobsRequest.py
aliyunsdkdts/request/v20200101/DeleteMigrationJobRequest.py
aliyunsdkdts/request/v20200101/DeleteSubscriptionInstanceRequest.py
aliyunsdkdts/request/v20200101/DeleteSynchronizationJobRequest.py
aliyunsdkdts/request/v20200101/DescribeChannelAccountRequest.py
aliyunsdkdts/request/v20200101/DescribeCheckJobsRequest.py
aliyunsdkdts/request/v20200101/DescribeClusterOperateLogsRequest.py
aliyunsdkdts/request/v20200101/DescribeClusterUsedUtilizationRequest.py
aliyun_python_sdk_dts-5.1.29.dist-info/LICENSE
aliyun_python_sdk_dts-5.1.29.dist-info/METADATA
aliyun_python_sdk_dts-5.1.29.dist-info/WHEEL
aliyun_python_sdk_dts-5.1.29.dist-info/top_level.txt
aliyun_python_sdk_dts-5.1.29.dist-info/RECORD
